<Signature xmlns="http://www.w3.org/2000/09/xmldsig#" Id="AuthorSignature">
<SignedInfo>
<CanonicalizationMethod Algorithm="http://www.w3.org/2001/10/xml-exc-c14n#"></CanonicalizationMethod>
<SignatureMethod Algorithm="http://www.w3.org/2001/04/xmldsig-more#rsa-sha512"></SignatureMethod>
<Reference URI=".git%2FCOMMIT_EDITMSG">
<DigestMethod Algorithm="http://www.w3.org/2001/04/xmlenc#sha512"></DigestMethod>
<DigestValue>2eDgeXtW1ngk7pRvTqGyPI0RYPP8k1a46qWgymDWBZ//AFKUWhDKPJiKG8zU7uKgjuWVoJFzfh/O
pSQXsss5dQ==</DigestValue>
</Reference>
<Reference URI=".git%2FFETCH_HEAD">
<DigestMethod Algorithm="http://www.w3.org/2001/04/xmlenc#sha512"></DigestMethod>
<DigestValue>DZclqLZK63bRJrZ/U4RtMeLTbeRxKjsl3Y5ltWXWJGFI7dU8NXy+mL+NY9MC0jwwg1oya2PXXpT6
IWIg7KOFGQ==</DigestValue>
</Reference>
<Reference URI=".git%2FHEAD">
<DigestMethod Algorithm="http://www.w3.org/2001/04/xmlenc#sha512"></DigestMethod>
<DigestValue>i8nxfwYow86TXdrD0VzUgqdWeX8ZKHpKW5bg4883z5DEIZSbLoLWVxSydMi0VaxSLYgSO+g+4u/Y
XqxfupTKgA==</DigestValue>
</Reference>
<Reference URI=".git%2Fconfig">
<DigestMethod Algorithm="http://www.w3.org/2001/04/xmlenc#sha512"></DigestMethod>
<DigestValue>iw62rmPwXcDhIk+5mbloYrukZ2bS9LMImZ66vtzU27Cg0wedLSzceLA6NCGzEEMbreTM5yRmrMSd
xIT+mDSAFg==</DigestValue>
</Reference>
<Reference URI=".git%2Fdescription">
<DigestMethod Algorithm="http://www.w3.org/2001/04/xmlenc#sha512"></DigestMethod>
<DigestValue>9+FS91sSTD4cXRLwBCdynZ7sTiwb9w12BkQKZgDQAzZ+sXgzHnWrl2phSW55wsgiAghJ0o/9FwlG
OXuTRhG0cQ==</DigestValue>
</Reference>
<Reference URI=".git%2Fhooks%2Fapplypatch-msg.sample">
<DigestMethod Algorithm="http://www.w3.org/2001/04/xmlenc#sha512"></DigestMethod>
<DigestValue>U2zOgE2E4lgTmT790kBTe1LQDOnNzs8ZgvhQltVqUhKQEEyCXACzcLJ1IgGVKpYWo/TijF0npbTk
hCEBov+b7g==</DigestValue>
</Reference>
<Reference URI=".git%2Fhooks%2Fcommit-msg.sample">
<DigestMethod Algorithm="http://www.w3.org/2001/04/xmlenc#sha512"></DigestMethod>
<DigestValue>1rt/p0f0YlrfGHf1RlZcvoEsp91BaPfpBo5nMlVdhzfrpUlUbPWUZknj843oLRc6r5wWCkyflEVl
Uli0xflV6w==</DigestValue>
</Reference>
<Reference URI=".git%2Fhooks%2Ffsmonitor-watchman.sample">
<DigestMethod Algorithm="http://www.w3.org/2001/04/xmlenc#sha512"></DigestMethod>
<DigestValue>9aTSv/kxYethuZAv901e4g3jMW8rHFrUkpnerxrfIxhIxVAbbkqEDluJh5H4bGbu1vOwX/VzBzZ0
F3ozofKunA==</DigestValue>
</Reference>
<Reference URI=".git%2Fhooks%2Fpost-update.sample">
<DigestMethod Algorithm="http://www.w3.org/2001/04/xmlenc#sha512"></DigestMethod>
<DigestValue>RzrRJGQlcWVidr+Duf9jqxgE08I6W9rlI5HG9wqJSEmsYMEMnTHe/zk4kizoO2ix5gwRWSu/fqUD
9KzTmWjO+g==</DigestValue>
</Reference>
<Reference URI=".git%2Fhooks%2Fpre-applypatch.sample">
<DigestMethod Algorithm="http://www.w3.org/2001/04/xmlenc#sha512"></DigestMethod>
<DigestValue>y3iqfpucFG5dtl2G3YPwTitpQqBvq1DHBKD9kAaD87atEWTnSv4vJn9tqRzf8LmrB3E+Es78b410
G13xlPT9pg==</DigestValue>
</Reference>
<Reference URI=".git%2Fhooks%2Fpre-commit.sample">
<DigestMethod Algorithm="http://www.w3.org/2001/04/xmlenc#sha512"></DigestMethod>
<DigestValue>fPsKWKvtGRXuGyYaHGYcfi3upOkif3f1h1rxolyC4ZJFuhLcsvUFLZlNDoGjRl2vN/nYxnDhf5yW
dC9g/fqqVg==</DigestValue>
</Reference>
<Reference URI=".git%2Fhooks%2Fpre-merge-commit.sample">
<DigestMethod Algorithm="http://www.w3.org/2001/04/xmlenc#sha512"></DigestMethod>
<DigestValue>5NwgRJT1Bi76MDKwDGRwek84l4BASCUBs+CF8HHj7lqXN9U35qUgAs606+K/4J5VXF2WlYHoCz66
KpIgFcZ5YA==</DigestValue>
</Reference>
<Reference URI=".git%2Fhooks%2Fpre-push.sample">
<DigestMethod Algorithm="http://www.w3.org/2001/04/xmlenc#sha512"></DigestMethod>
<DigestValue>zJi74OOGXiAjrwRBbhBonjrs0/OSjPkMKswNPXMGOIiGd5AlyJZ8jqGYrx9P4p0Wxl1OHVRseo+l
E/W6ffFoUA==</DigestValue>
</Reference>
<Reference URI=".git%2Fhooks%2Fpre-rebase.sample">
<DigestMethod Algorithm="http://www.w3.org/2001/04/xmlenc#sha512"></DigestMethod>
<DigestValue>ANIdXXI4bD2bWhw2uoUgH3MFVqgpXUNTr1SveJKrgQENQq/yCewf2mHFTk3aNzfOpf2mTwnUDOUA
SuKCOVZQJQ==</DigestValue>
</Reference>
<Reference URI=".git%2Fhooks%2Fpre-receive.sample">
<DigestMethod Algorithm="http://www.w3.org/2001/04/xmlenc#sha512"></DigestMethod>
<DigestValue>7gjBH6t+iWsuCcJBlUunZAM4sSx1zYBA2vBTwxsvIiNteg3qxzb4nTBSNjEv209WCjjU2N69zJ3N
0jstl1kH1Q==</DigestValue>
</Reference>
<Reference URI=".git%2Fhooks%2Fprepare-commit-msg.sample">
<DigestMethod Algorithm="http://www.w3.org/2001/04/xmlenc#sha512"></DigestMethod>
<DigestValue>UOyKDdmEJ+gKgqjYzkRGKoRYduFZTJ0OiUg86aiqrWFu3qDlxFwbtp2P5/UgxvImDW+jUNd7QAiZ
w643XpZb+w==</DigestValue>
</Reference>
<Reference URI=".git%2Fhooks%2Fpush-to-checkout.sample">
<DigestMethod Algorithm="http://www.w3.org/2001/04/xmlenc#sha512"></DigestMethod>
<DigestValue>WG77aiBvc9ipRWEmYVOmJOJ1ODC8QxooO+2ZjEasAKnfSZXd/QqoUrGiK0ZyyA8sM87j/i4zIeOS
/0zvJtv3Xg==</DigestValue>
</Reference>
<Reference URI=".git%2Fhooks%2Fupdate.sample">
<DigestMethod Algorithm="http://www.w3.org/2001/04/xmlenc#sha512"></DigestMethod>
<DigestValue>vjeAl0WJ0G7dum+gqhWj49/jkOKCehpq5cuD1qxH5575sbu1PwZzcvjccNsDUNN3DnhTf9PP5zQg
D/gk7KTK2g==</DigestValue>
</Reference>
<Reference URI=".git%2Findex">
<DigestMethod Algorithm="http://www.w3.org/2001/04/xmlenc#sha512"></DigestMethod>
<DigestValue>b8u4HEVI5Q8QmVBOXmQvDbeXt0bKwo95vX1J2z3o/sHL26UuvGXKfvfiqlUmC5CAttBgzsbbZ8Il
8FI72sek8A==</DigestValue>
</Reference>
<Reference URI=".git%2Finfo%2Fexclude">
<DigestMethod Algorithm="http://www.w3.org/2001/04/xmlenc#sha512"></DigestMethod>
<DigestValue>mCjG7N+RvxF0FuF/TunK7i4eN7b7ALn/BANazhejCJudCiXGuqEEbA4cYtPaiIOOj8p06oKXPWuX
WQX95Y8wcg==</DigestValue>
</Reference>
<Reference URI=".git%2Flogs%2FHEAD">
<DigestMethod Algorithm="http://www.w3.org/2001/04/xmlenc#sha512"></DigestMethod>
<DigestValue>qvVCRqf72ZypOxoX2KN6tXXBpGz84qnJu53TkCfXdoM8J4NnOa6Wej97frfvYREUT2EBcpQ7LqnZ
I+3iXeo+fw==</DigestValue>
</Reference>
<Reference URI=".git%2Flogs%2Frefs%2Fheads%2Fmain">
<DigestMethod Algorithm="http://www.w3.org/2001/04/xmlenc#sha512"></DigestMethod>
<DigestValue>BxJZ3XBWuPmOFukODWBQyEoZ+ty8bky0PZJhw4TLhdyFX+3kj1hvOdl7kEAONZtVS1QjsqswXsqU
J1pHQZIeGw==</DigestValue>
</Reference>
<Reference URI=".git%2Flogs%2Frefs%2Fremotes%2Forigin%2Fmain">
<DigestMethod Algorithm="http://www.w3.org/2001/04/xmlenc#sha512"></DigestMethod>
<DigestValue>9AnIJl6PRs7cYJFitJ4X3UA6qGUqQaNXp8Wy3BXcZomqNn9xbCuWVUxJZdWhKjKq7i57KyoW5er7
AQf4J8dQRw==</DigestValue>
</Reference>
<Reference URI=".git%2Fobjects%2F00%2F0e937c65dfc69d3d49fa60e95b48f34dc66f80">
<DigestMethod Algorithm="http://www.w3.org/2001/04/xmlenc#sha512"></DigestMethod>
<DigestValue>txHPcHiZ7H3OOvbZHtC8xxTil2YNGtsZERe3oVPmPSdXbq5R2CaxaY9TchLA7qh8H0SnUmMj4Xho
Ni6SBxEDsQ==</DigestValue>
</Reference>
<Reference URI=".git%2Fobjects%2F00%2F81b9919997ddb01d1aa92b3d19ed96a721ade6">
<DigestMethod Algorithm="http://www.w3.org/2001/04/xmlenc#sha512"></DigestMethod>
<DigestValue>IpwUvwVZ5RMoTq31Z5wRM19jzBbjrAUEY4KcpA+nYm7+RHS7uTh/odwwaXwUvRhtbBGBW7y+kN+o
ZT6+bHFftw==</DigestValue>
</Reference>
<Reference URI=".git%2Fobjects%2F04%2F2c3f6f27b07357a866178f36b97df8c02ab7da">
<DigestMethod Algorithm="http://www.w3.org/2001/04/xmlenc#sha512"></DigestMethod>
<DigestValue>jpNij2BnzT8wHPK4HYcmCrBcudR8yHcMWPUq7EjMuUkhIQYIuXnMwf7PkTxOPPb2cghk8HdRMA2l
MnYXO77hPg==</DigestValue>
</Reference>
<Reference URI=".git%2Fobjects%2F05%2F5a105db1e963f5330d7f71c83bca682ee82880">
<DigestMethod Algorithm="http://www.w3.org/2001/04/xmlenc#sha512"></DigestMethod>
<DigestValue>inGzWLjl/BPZEc63v0F2u0Xb+y6aEehda53G/oh4BlvGe+KYuRSURlT+baWH8tA/LWBz5Guhgc2S
g14YvvpaDA==</DigestValue>
</Reference>
<Reference URI=".git%2Fobjects%2F05%2Fbd71b6ec2c1982d1e8a5653073281994564ae8">
<DigestMethod Algorithm="http://www.w3.org/2001/04/xmlenc#sha512"></DigestMethod>
<DigestValue>rkyNMBK1NE97/qj7ogMNyRsxmBqim1TOPPykinFotnQZ8bA/YlGmUPGAbMwKSjMRSHWfoaWczAfD
2D1y3pk6Hg==</DigestValue>
</Reference>
<Reference URI=".git%2Fobjects%2F0a%2F34467048cf6b1f55e2d3a6ec71294b022cc63b">
<DigestMethod Algorithm="http://www.w3.org/2001/04/xmlenc#sha512"></DigestMethod>
<DigestValue>f9VwsktqLvBEJvCATJfa7fedTqcZh78yq2q7mXZZ5AtuN8yoKkxVSOXzllqR2OEsqBuikzlywMys
4FMg41bUVQ==</DigestValue>
</Reference>
<Reference URI=".git%2Fobjects%2F10%2F108a8c549d8b823976ec6ff03f3893b8278459">
<DigestMethod Algorithm="http://www.w3.org/2001/04/xmlenc#sha512"></DigestMethod>
<DigestValue>i464PIls5mCCacwIczRIf47Xv7q4DIFrdaFArTE9yyYJUHzRedpnQ01HAWcxHed9Rpifjo+zL6J9
O3dyQxcNfg==</DigestValue>
</Reference>
<Reference URI=".git%2Fobjects%2F10%2F94992d63882b6db721b4d8f656987fadada924">
<DigestMethod Algorithm="http://www.w3.org/2001/04/xmlenc#sha512"></DigestMethod>
<DigestValue>GO/Dt2r0dfJMxC0BRlBVXLtXbuAZbJO8xHNOW40tVR9ilpO9FNh10vyavgHcQCNND6zUWRK/cSLh
SJoRWTt/vQ==</DigestValue>
</Reference>
<Reference URI=".git%2Fobjects%2F12%2Fc1bcaa18e94153badb4901ff7724a7b92c1993">
<DigestMethod Algorithm="http://www.w3.org/2001/04/xmlenc#sha512"></DigestMethod>
<DigestValue>EVNEPOTzKQI3y/zSpyoYESJXWt4tdyxYx71TYjRquDguySmBl/k77apB5LFiBk2DKHl0KcnqqmfO
TSCUtca9ZA==</DigestValue>
</Reference>
<Reference URI=".git%2Fobjects%2F1f%2F0208805de8d0af7fb52beb747590a1ad6038c4">
<DigestMethod Algorithm="http://www.w3.org/2001/04/xmlenc#sha512"></DigestMethod>
<DigestValue>M61iXljp9s17AlH5UvxLWYqb6mZTqCNloWDEO+xGEKeWlNq56EDRB1fN1laVxc7U0/yKylOoNf1S
J35WuEjk8A==</DigestValue>
</Reference>
<Reference URI=".git%2Fobjects%2F23%2F86351522759e2a0b051a0cb0e4b35a56dff088">
<DigestMethod Algorithm="http://www.w3.org/2001/04/xmlenc#sha512"></DigestMethod>
<DigestValue>YiraHssjLWTE798HO9heK3N/ehuKxUDsnwFkKMBY+kWMOjA+WdvbtYinMHW75Ad7oKKRSb5VTbH0
Sg2hYA3b8A==</DigestValue>
</Reference>
<Reference URI=".git%2Fobjects%2F25%2Fcb955ba23571f6fefd57cecf5f67454210bbc8">
<DigestMethod Algorithm="http://www.w3.org/2001/04/xmlenc#sha512"></DigestMethod>
<DigestValue>3fNKW1BWqPC7ZtTfiMrHu3EonfUqY2qZj+NMtQvTN9+zQc5/qDxfkGra2KJvGO6llPykkcrhNmEn
7glg9L/pOw==</DigestValue>
</Reference>
<Reference URI=".git%2Fobjects%2F35%2F42170b847a064894983317fdd3dba5fbb7a812">
<DigestMethod Algorithm="http://www.w3.org/2001/04/xmlenc#sha512"></DigestMethod>
<DigestValue>l5jMBRhDcjVwCAkLsPGMBWPf2uV2BXy6mLZMp+BaugTxVRcy9JQjtp/xLioyKFuaLO7302twnDiF
iSIRwjWIPg==</DigestValue>
</Reference>
<Reference URI=".git%2Fobjects%2F3b%2Fd5d0a4803967bc0bf72a7dd66d7e292ed2e586">
<DigestMethod Algorithm="http://www.w3.org/2001/04/xmlenc#sha512"></DigestMethod>
<DigestValue>RwV/EqNaZMcunMbHXN41HJgQnmf73X1+q+WsYYD2TYaGM+zpISFswED1aEuQFNFdCcjVbI5fNtQH
vNVhiLdH/w==</DigestValue>
</Reference>
<Reference URI=".git%2Fobjects%2F3d%2Fdbcf3257c01764a879a28a18b6a6ad957bc297">
<DigestMethod Algorithm="http://www.w3.org/2001/04/xmlenc#sha512"></DigestMethod>
<DigestValue>zKU47ZbPtM7WIslTUqbAJyi8hxLsBIiJZIQe0oTh55z1hTrZwaKMB6MRnY1WJ5hcHIqoipIf58Wq
y+nIu/iTrw==</DigestValue>
</Reference>
<Reference URI=".git%2Fobjects%2F3d%2Fdcc05e2d205f7488ba9ea84b1a83db0ba27281">
<DigestMethod Algorithm="http://www.w3.org/2001/04/xmlenc#sha512"></DigestMethod>
<DigestValue>OMVG+TWGyTClZ1d1adhuj/e3V9urtEuaG0XwL/MoYoX5wVyVKyjLe7Ur4d5Z8OOp20GteMOpEiAD
NCWqSP24Ew==</DigestValue>
</Reference>
<Reference URI=".git%2Fobjects%2F3f%2F8e74c70f23ec0f8e79df60150b5e7086ec3128">
<DigestMethod Algorithm="http://www.w3.org/2001/04/xmlenc#sha512"></DigestMethod>
<DigestValue>2llzmr8KflWI/Sp/D0OWz2SpW+Q0oSTYYcxMI3WySRKy39McRCfAvYn+WKGSf1evdIPTMCn7ky6g
BV+KGPsNiQ==</DigestValue>
</Reference>
<Reference URI=".git%2Fobjects%2F4a%2F0af40baef878b747eaf9e3d1081e3447609ff5">
<DigestMethod Algorithm="http://www.w3.org/2001/04/xmlenc#sha512"></DigestMethod>
<DigestValue>Gu3WxCG+tmmcfhR0iHls2BjjLsKvVwBRG+1EQ+cCKnBYprjsi+ui/iDSba2pBC6EOvIyEGshSGam
7RLc21k6kQ==</DigestValue>
</Reference>
<Reference URI=".git%2Fobjects%2F4a%2Fcb16272ebffb62e8f0a9a01544140760a50bab">
<DigestMethod Algorithm="http://www.w3.org/2001/04/xmlenc#sha512"></DigestMethod>
<DigestValue>fp3qtO9TGfANvU7/LeYYTU/UeXfDu1faHMW/8oWpV0I9GoM56yZyd5s3AkHbXrLMUiBwjjWyGr3g
q9ySGDTrDw==</DigestValue>
</Reference>
<Reference URI=".git%2Fobjects%2F56%2Fcd496ffc9b92e8d0612bb949b93400290d3f37">
<DigestMethod Algorithm="http://www.w3.org/2001/04/xmlenc#sha512"></DigestMethod>
<DigestValue>+RrbRxcHI/w30tgde0I0CeG9lVsm42rtiMI8E1BP+tsvPaRDU7CE9v9w8kTAtnMdfljN0EgOwAkp
hxtkAjSh/g==</DigestValue>
</Reference>
<Reference URI=".git%2Fobjects%2F58%2F5e8cefe998306475a4dd20aad90c514519bb62">
<DigestMethod Algorithm="http://www.w3.org/2001/04/xmlenc#sha512"></DigestMethod>
<DigestValue>wsSTUvlQ0OTIzFEN8VQtCkjDNWCudpU9Rq9ukmWd7mjAQRjPdVC0eTGxK7hlMMVoiiuTcUS+n1FI
fxEWKliENA==</DigestValue>
</Reference>
<Reference URI=".git%2Fobjects%2F58%2Fa4edc8fa2b3e460dd4d5c53c7af1ac6bcd8651">
<DigestMethod Algorithm="http://www.w3.org/2001/04/xmlenc#sha512"></DigestMethod>
<DigestValue>7DCSrI8lC4vGt2JARk0/RCRa+oZoQQjhtMCnBI+sRxo6jrrABIT1xNNH6he2sKD22ZaFtqpCH3LA
/USxJmi9Ug==</DigestValue>
</Reference>
<Reference URI=".git%2Fobjects%2F5c%2Fa0b7769013920648b17f3f51ba3e88139fdf0e">
<DigestMethod Algorithm="http://www.w3.org/2001/04/xmlenc#sha512"></DigestMethod>
<DigestValue>Y5dWCiieJbJUMxusX1HC48UBCtGxBzqTFVnf05VA20UQApqxU9QaC1mGLPyVSXoRuuuVf1RBHul+
193mMjQGLw==</DigestValue>
</Reference>
<Reference URI=".git%2Fobjects%2F5d%2Fdc6bd5f24cf4e67a53e20384dfc868809d10b3">
<DigestMethod Algorithm="http://www.w3.org/2001/04/xmlenc#sha512"></DigestMethod>
<DigestValue>VLgli7cw5IfmTSpTyqPXbe7gN1bWPdWEVbxF5h+Zg4KkVBz/bRgpLVmGBZUL6RbZuASUvFK8YR5s
RlP3EXtYMw==</DigestValue>
</Reference>
<Reference URI=".git%2Fobjects%2F5e%2F2da66d47648fbeb2ddad1fb164db75fd2e077c">
<DigestMethod Algorithm="http://www.w3.org/2001/04/xmlenc#sha512"></DigestMethod>
<DigestValue>GaOdF+YTjtdDyIzenOMTTB93ZZ70nUeX7iLaFE61HB2yPHZ4gpSarLBCwEzOsg8tqaNLdymzNQC5
tRa3cD0Mcw==</DigestValue>
</Reference>
<Reference URI=".git%2Fobjects%2F68%2Ff38887ff3358c0612456685094c979f673fdf6">
<DigestMethod Algorithm="http://www.w3.org/2001/04/xmlenc#sha512"></DigestMethod>
<DigestValue>s80JSEBY2cLdK8Z1IMw5dsboXcdCPYFbUvsPVQP4QUsAJoVCGqCqArOkQYNEU859FLKjx/Em4hge
ABZFjfjWeA==</DigestValue>
</Reference>
<Reference URI=".git%2Fobjects%2F69%2F9e6a224c0664315838622422a1feaacd622fcf">
<DigestMethod Algorithm="http://www.w3.org/2001/04/xmlenc#sha512"></DigestMethod>
<DigestValue>gfyXzdoTePKEQBmH4fqBiA0vE/1lXK1wx39tmVvJC2JqcXEWb1phgtvP9PhY4428V/H1OdxPEoQS
frDr4/qt3g==</DigestValue>
</Reference>
<Reference URI=".git%2Fobjects%2F69%2Fdddc0da673884dcf90447482424f7c2aba411a">
<DigestMethod Algorithm="http://www.w3.org/2001/04/xmlenc#sha512"></DigestMethod>
<DigestValue>lX3iuEEGk4twEY6jgIKs95GyrlFRstofM/34drP/DmuWtcqGCM/2AxTk+3ou3YycPcYe+dchInh2
opj5Uc/5sQ==</DigestValue>
</Reference>
<Reference URI=".git%2Fobjects%2F6b%2F2aaa7640726588bcd3d57e1de4b1315b7f315e">
<DigestMethod Algorithm="http://www.w3.org/2001/04/xmlenc#sha512"></DigestMethod>
<DigestValue>41nMNE/omsejXfIctQtLGg9Kk5hiB537nDEKIBx/qf32q5q2uohsHDIPv95/rX5oiNOTIan6NAty
7eKIUVezOQ==</DigestValue>
</Reference>
<Reference URI=".git%2Fobjects%2F79%2F18fb542b2a06996adbc781dfdb83553724a2d2">
<DigestMethod Algorithm="http://www.w3.org/2001/04/xmlenc#sha512"></DigestMethod>
<DigestValue>RzDIK4qtY4gu9h1JwGs8+FjsD/PApvyHstiDrxdbcr4ew3EiBLvuqLm+MCuzWI+BkZ84Z/tievk3
sb3xBA0FKA==</DigestValue>
</Reference>
<Reference URI=".git%2Fobjects%2F7b%2F39e2d752710d41daa1c6bb278ca7f534c3c32c">
<DigestMethod Algorithm="http://www.w3.org/2001/04/xmlenc#sha512"></DigestMethod>
<DigestValue>b7F4qoEr+6xDgxCOJF/wTLow3nQgRHIkMUEZKAdAT/xkn885bAMKmO+cL62FwGkNMbrawrhjPKk0
ub3ne1+9Uw==</DigestValue>
</Reference>
<Reference URI=".git%2Fobjects%2F7f%2F2b55183784b2cd205eaf6a2e61a4f3d790bfa8">
<DigestMethod Algorithm="http://www.w3.org/2001/04/xmlenc#sha512"></DigestMethod>
<DigestValue>479L+66zw6OLPKP7Tgeh1tOumttP0zN7q/mvvRR/pEe4GFCtOGa8W6fuInrpa8h9rHaj71SrdXcP
RtSkN3rwIw==</DigestValue>
</Reference>
<Reference URI=".git%2Fobjects%2F7f%2Ff742806b0c767ea0c6a313a497056007e03dd6">
<DigestMethod Algorithm="http://www.w3.org/2001/04/xmlenc#sha512"></DigestMethod>
<DigestValue>lPXXoAnrKZ3q4sru4hxleopNtY49TpAXat+8e5EtB8hpUi9QSUzlavsS3XmZxAAk5x+UHUx4PV6+
2NpEhfLAmw==</DigestValue>
</Reference>
<Reference URI=".git%2Fobjects%2F80%2F834ad16df4a390d44de7adc5356840a793cb76">
<DigestMethod Algorithm="http://www.w3.org/2001/04/xmlenc#sha512"></DigestMethod>
<DigestValue>HbyDieZjK+nvEh7iOxQou5v+eogU+lFzHw5sqoS0GSUNqNWQmLsfIfm0PAOHos9RP2hnIqHp0Tmn
tHBLAxsFtA==</DigestValue>
</Reference>
<Reference URI=".git%2Fobjects%2F85%2F1c296e6f4aafbda8f9e3b33838515a853f9e06">
<DigestMethod Algorithm="http://www.w3.org/2001/04/xmlenc#sha512"></DigestMethod>
<DigestValue>T3p+soCBlzGztOZgH9P2l6pfhU47/wJO3w84AAwOmGKqQOepeT2FpmxQIKclRQ/s8mDEoHWpy7Se
+n194r9EZQ==</DigestValue>
</Reference>
<Reference URI=".git%2Fobjects%2F8b%2F137891791fe96927ad78e64b0aad7bded08bdc">
<DigestMethod Algorithm="http://www.w3.org/2001/04/xmlenc#sha512"></DigestMethod>
<DigestValue>Nr9PZFhnhY2awVCtJXwW7ihACHuzrSrDZJjRweIngsly5vKoPp5SO5YmX2o5QllDpWmEXI450sF+
jcdJPFc7VA==</DigestValue>
</Reference>
<Reference URI=".git%2Fobjects%2F8f%2F7283b7eaa918acf521a562fa89e0cea9e32e5e">
<DigestMethod Algorithm="http://www.w3.org/2001/04/xmlenc#sha512"></DigestMethod>
<DigestValue>1XzmYMS66CS8SPdMje4A+irrd8pEDHfkyLqv6DsGyGuRR4SLdNyRV6eqggY8XFvp+OG7CKKsq9WB
sYE+1Blizw==</DigestValue>
</Reference>
<Reference URI=".git%2Fobjects%2F98%2F3c883493a0ae561b9592d54ea8204042b4b6fb">
<DigestMethod Algorithm="http://www.w3.org/2001/04/xmlenc#sha512"></DigestMethod>
<DigestValue>6dS/lev0BrPcZv+D/92F3H/ObJP5KWMGg9k4tC71pBvTj6LtBo+gWr4U1sl6QkwfW7w2Z7qX26n4
wg+J+j6g5g==</DigestValue>
</Reference>
<Reference URI=".git%2Fobjects%2F98%2F7a62736a1ce36784a181c976f641b4d9824750">
<DigestMethod Algorithm="http://www.w3.org/2001/04/xmlenc#sha512"></DigestMethod>
<DigestValue>SUihJVmTjPKHEupIfYyt4FzfJuF/w9n4l5FGi4eG0UrYVSy3j44WMyYkVZcoTPLrLtamTr4cx/XR
nLgf88URlQ==</DigestValue>
</Reference>
<Reference URI=".git%2Fobjects%2F98%2Fd8634ae918e69727b34940eb6849f729c8645c">
<DigestMethod Algorithm="http://www.w3.org/2001/04/xmlenc#sha512"></DigestMethod>
<DigestValue>Z9XrTVRN5WIO1CgvgC1v5gQHoSaYC3cnwvJVmZ+7S5eFgyoJZDa6yE7+SUElhwtXGjUKokNbx9pS
TXmd1DskoA==</DigestValue>
</Reference>
<Reference URI=".git%2Fobjects%2F9b%2F31925fe86ed6daa0f26b90765bfbd7acad28de">
<DigestMethod Algorithm="http://www.w3.org/2001/04/xmlenc#sha512"></DigestMethod>
<DigestValue>Ij+WbCICw9E8u3WaNdu1M9DVfPMNRNdIneUtNsn/BYt6eqcjzP9zu3b+RYe1RBs16Lg+zb3SE9Al
3r9SeY4G1Q==</DigestValue>
</Reference>
<Reference URI=".git%2Fobjects%2F9e%2F390f501d055f97f1a023eb11d0916f4992c3e9">
<DigestMethod Algorithm="http://www.w3.org/2001/04/xmlenc#sha512"></DigestMethod>
<DigestValue>OxoVM1YeaQasWK9qrURqEh332713rNmm3NwoVFkcWzADxbmh10anlxX5sVv/QyaDWvXefzQ7gpvS
0sf3OEbxQw==</DigestValue>
</Reference>
<Reference URI=".git%2Fobjects%2Fa4%2Fee3cbc9a7fb4242b2f2becb901674986dc4389">
<DigestMethod Algorithm="http://www.w3.org/2001/04/xmlenc#sha512"></DigestMethod>
<DigestValue>2zNwJIaYrww6kivgWmxkwMChFu7G4t82PFIrmkjInFwefiQsq6J63vQzNQDkqbFC4QguPKdgn72q
73PiVMwkKw==</DigestValue>
</Reference>
<Reference URI=".git%2Fobjects%2Fab%2F93bafe06e3871eb5d4daa0651220255d2eba51">
<DigestMethod Algorithm="http://www.w3.org/2001/04/xmlenc#sha512"></DigestMethod>
<DigestValue>G43fLJshwl8xTglvJ7wcrRyAgInvTrJiWtO5w7cjwDmZFF6jGf1B4E783TLKqFFENBup5rGQnivJ
cwpt/ovSeQ==</DigestValue>
</Reference>
<Reference URI=".git%2Fobjects%2Fad%2F057e4b7299f6e42ea50a026a0f974a956430bf">
<DigestMethod Algorithm="http://www.w3.org/2001/04/xmlenc#sha512"></DigestMethod>
<DigestValue>quktQKWb2cMLDUlZgJspCcck7wSQj6vbrpizbp4ntIkoCsI1TVbU0ps3BAna3QILZczJoOpcqF8q
er9KJwQV8Q==</DigestValue>
</Reference>
<Reference URI=".git%2Fobjects%2Faf%2Fc47759d362767c805309f560a6dff94be21a83">
<DigestMethod Algorithm="http://www.w3.org/2001/04/xmlenc#sha512"></DigestMethod>
<DigestValue>DIwygNJCrqjqeaYJ5pBIZJMuNjUq3zv5qPgl1qz9HHquzlCS+hNo08+TYJdbHP6SctYWcjcR+nbR
Gchdz2RPZQ==</DigestValue>
</Reference>
<Reference URI=".git%2Fobjects%2Fb2%2F97eac084d2cbbeb4e09b646d5d0aaa3a078b09">
<DigestMethod Algorithm="http://www.w3.org/2001/04/xmlenc#sha512"></DigestMethod>
<DigestValue>Yx4mS5/Gjt81Ljse3SkUruY41GbXHuhwJ8R7/gmGpQQ2WpXGA4eQ3eg+5w7eOAdeWQ9iiWJaVaRj
ojszV7tDeg==</DigestValue>
</Reference>
<Reference URI=".git%2Fobjects%2Fb5%2F8a0712ace48af248eb584884bc29c027663fb5">
<DigestMethod Algorithm="http://www.w3.org/2001/04/xmlenc#sha512"></DigestMethod>
<DigestValue>ZkKylBE7JnATloK9jbe+tsdDQJpsfaL+aovZKXh5W84bdaMQsp3ZR0RQ2mrcvJRDEQ6BEt6XPO6L
ANHObZH5kQ==</DigestValue>
</Reference>
<Reference URI=".git%2Fobjects%2Fba%2F10e58a4cfa9bcf16900233c94ac0c60bbcc765">
<DigestMethod Algorithm="http://www.w3.org/2001/04/xmlenc#sha512"></DigestMethod>
<DigestValue>RfhhDX5T/XHbdE8GqwThxCiuncxfyPBU8cYcaiPhsRID7jkeHkf6/uRs8F3iPd2MI5eizITsSNJD
A89rzTC+zg==</DigestValue>
</Reference>
<Reference URI=".git%2Fobjects%2Fba%2F9daf64cf4356eec75624ed569cfe14c4c54992">
<DigestMethod Algorithm="http://www.w3.org/2001/04/xmlenc#sha512"></DigestMethod>
<DigestValue>OGFQtvrYBVCWatHOtUcIm9i3J0RDd62yi21WdnqZY5TKHcGlZSIhas1SOKoCqIhiByeFgvQnzKo0
vqjDpymEpw==</DigestValue>
</Reference>
<Reference URI=".git%2Fobjects%2Fbf%2Fec1b7bbd16cdbc70bdf12d7d5b7e553fecde8e">
<DigestMethod Algorithm="http://www.w3.org/2001/04/xmlenc#sha512"></DigestMethod>
<DigestValue>5pojXpjjo2hw2gw1qyVUSV+mYhijbMgvj+ySCRU6MP/XuVwEY/FqO5/Tqhv4kySMXjhd5bGsEK66
B0XtOuBgnA==</DigestValue>
</Reference>
<Reference URI=".git%2Fobjects%2Fc4%2F4fcad87d3dad8a20d81c5599c10bbc2c8671d4">
<DigestMethod Algorithm="http://www.w3.org/2001/04/xmlenc#sha512"></DigestMethod>
<DigestValue>iYBIXr07ehjUeDklEdvNeR8YpSx+Ob4LW8ir3DjqdwSYZt70J0cWqmEQ7v4jQj7cZQWx81bFh3ad
9Sm7rNmhJQ==</DigestValue>
</Reference>
<Reference URI=".git%2Fobjects%2Fc4%2F87c068cae1a73c7bf7239555c1329610507ec9">
<DigestMethod Algorithm="http://www.w3.org/2001/04/xmlenc#sha512"></DigestMethod>
<DigestValue>w42LFlWQJuOx/27OP6WvYcfD0m1krIHAPfFDL2FARC57PtvbzbxuzNHWeoW2MQVfdd8uXgb2H9l0
QDdZa3i/eg==</DigestValue>
</Reference>
<Reference URI=".git%2Fobjects%2Fcc%2F9e760490235d3343f1401828cc1aba69aaaaf0">
<DigestMethod Algorithm="http://www.w3.org/2001/04/xmlenc#sha512"></DigestMethod>
<DigestValue>tHZpqZwfwgziAzgaXKSnpCLdYBbudWcbpJCe/esguArsgTmHBY3mmVyXC40r+ouNOO8ubYuzmZK6
v29J8ze9Ww==</DigestValue>
</Reference>
<Reference URI=".git%2Fobjects%2Fcd%2Fbe4d8fd70404be4761983ec5a61c9b1df43f88">
<DigestMethod Algorithm="http://www.w3.org/2001/04/xmlenc#sha512"></DigestMethod>
<DigestValue>i15nHh5FjLMofDY1Y6M1Kk+mOlqUjfldOIflYwPIyBlJI70PrWejIPWJzNrXDLwfrg8Iow9ZCOUE
WcPIRa+e+Q==</DigestValue>
</Reference>
<Reference URI=".git%2Fobjects%2Fce%2F57077255bdddc2efc52188e744b22ceb0a06d5">
<DigestMethod Algorithm="http://www.w3.org/2001/04/xmlenc#sha512"></DigestMethod>
<DigestValue>kqCOQloWZL/nxh+WNnwcG9L7QK7cQg2v7mqdbcjRk+mOmF5wIlN2d9BpfjLA2Jj8/Wd/RGKe645u
luBhLT/ygg==</DigestValue>
</Reference>
<Reference URI=".git%2Fobjects%2Fd2%2F32940bd85a379e8fa0a59b84976b81401a3845">
<DigestMethod Algorithm="http://www.w3.org/2001/04/xmlenc#sha512"></DigestMethod>
<DigestValue>OGAtKLSNrlgdrB9fKUpm7tlBcfv67Tq5wB6SwcsEAzd4nex2B+ATD4U0aIgSUFwWQJkYnL/MKIyV
Q16KMXdQZA==</DigestValue>
</Reference>
<Reference URI=".git%2Fobjects%2Fd5%2F16cc7695fd9f368dcf860717d8d4a3c57152a4">
<DigestMethod Algorithm="http://www.w3.org/2001/04/xmlenc#sha512"></DigestMethod>
<DigestValue>/EkCEEdFOWw/x2eyjSQopveg9fKOLAyGPx2dgr+ZcTVEO/X8dXwAku2ywJVIlcrTxrroO5iSDB0g
CazQkp0d5w==</DigestValue>
</Reference>
<Reference URI=".git%2Fobjects%2Fdf%2F453dccc5362d847d04d70ecce4923ea3c1fd51">
<DigestMethod Algorithm="http://www.w3.org/2001/04/xmlenc#sha512"></DigestMethod>
<DigestValue>Odl6XLbGSKGvQWSvKtM3GRANmOMa+PR1VIW9+U6MFgNokYjSpR+xpT5WoktRlpo6HCc3rYwnAfqW
sz0D2Kg74w==</DigestValue>
</Reference>
<Reference URI=".git%2Fobjects%2Fdf%2Ffc6b51349681ffb272ab899b3ef7c402cf49f9">
<DigestMethod Algorithm="http://www.w3.org/2001/04/xmlenc#sha512"></DigestMethod>
<DigestValue>bC8KOOd5wZqEjIHu7pgRrJpcNiR2NPg0ixpuNjxN8De6gKoaPPRuAYQGlUWM1OiY+xAgYmNSaulc
pEbsPVebkQ==</DigestValue>
</Reference>
<Reference URI=".git%2Fobjects%2Fe4%2Fcd2e85b9d7df63ad1dcf5c7f7f57e540fe9cc0">
<DigestMethod Algorithm="http://www.w3.org/2001/04/xmlenc#sha512"></DigestMethod>
<DigestValue>a/D1UoGOX8yAuEQoj9Eq8fdgyZep9xAiP0mK1Cl7UJ3Ts3AiQKnvRW0L/uBLQqKFFtKHY48go9TW
qregrfqbJw==</DigestValue>
</Reference>
<Reference URI=".git%2Fobjects%2Fe5%2F7e5573bbc81d1aa44ddf7859e57d235a68b671">
<DigestMethod Algorithm="http://www.w3.org/2001/04/xmlenc#sha512"></DigestMethod>
<DigestValue>fP7DdYFtatK/+yyk+SD4TiECJ0xcsD5rpFobtPJNSfoyPr32Os1PRrDSP0QN4rHcNo/eEehlNfv1
MaTjZSw1JA==</DigestValue>
</Reference>
<Reference URI=".git%2Fobjects%2Fe5%2Fd95dbece8d86398dee6458d316da380e872d87">
<DigestMethod Algorithm="http://www.w3.org/2001/04/xmlenc#sha512"></DigestMethod>
<DigestValue>2Rw1fzbHXopheuDxtYGtOEa4uymk9JzWeNCswQkg8TswEBwom2On1XiK5SV0v8T/KG5npeu1KHnP
fO6ASK9MDg==</DigestValue>
</Reference>
<Reference URI=".git%2Fobjects%2Fe6%2F9de29bb2d1d6434b8b29ae775ad8c2e48c5391">
<DigestMethod Algorithm="http://www.w3.org/2001/04/xmlenc#sha512"></DigestMethod>
<DigestValue>k8rhqWoGtg9OzZbaofQ2UA7mwaTC5ZjbPkKrafKi0A3aNjhj3HJ0LWZNRGvzlWjQvevThUyeCt2M
beoJSR8pnw==</DigestValue>
</Reference>
<Reference URI=".git%2Fobjects%2Feb%2F6b1c799849cdab62daf6172dfc7fe5390adc00">
<DigestMethod Algorithm="http://www.w3.org/2001/04/xmlenc#sha512"></DigestMethod>
<DigestValue>fl863+Ns+MIr9abVwtZPGFAgUrknuBa5m5rfVfa5j4kILou2DOKAj2v6TWJm28uUvtk00ieD3Hi/
gf030glspw==</DigestValue>
</Reference>
<Reference URI=".git%2Fobjects%2Ffd%2Fc3054f404188524a8253e1dd49afa312237bf6">
<DigestMethod Algorithm="http://www.w3.org/2001/04/xmlenc#sha512"></DigestMethod>
<DigestValue>dM9ex7LNIUggH1MbFGOMIMwIyNvF5ic+SyPwLPuu7VYRR0UOskaFxnReJoX2XGxkm4fRBe90u8Ar
D2IjVIzrcA==</DigestValue>
</Reference>
<Reference URI=".git%2Fobjects%2Ffe%2F0d872c279667b878acd49d3cf75fa71cd7fd2e">
<DigestMethod Algorithm="http://www.w3.org/2001/04/xmlenc#sha512"></DigestMethod>
<DigestValue>aEgsOGswsQbcAQHzdK9KKvPcGmrT7qRhjFyutKDLz2JmxchyGc+u5GHENTv/QSJ9Fmh27iLkzb4D
bVBSFnQueg==</DigestValue>
</Reference>
<Reference URI=".git%2Frefs%2Fheads%2Fmain">
<DigestMethod Algorithm="http://www.w3.org/2001/04/xmlenc#sha512"></DigestMethod>
<DigestValue>q0y7dYggZ5NSeK7nP9fUEF56fskDfIncDizlb03YvRZNeLetgn0okYtleuVuq4yzDxtN1RGB5Ki5
RvkJ9g9s7A==</DigestValue>
</Reference>
<Reference URI=".git%2Frefs%2Fremotes%2Forigin%2Fmain">
<DigestMethod Algorithm="http://www.w3.org/2001/04/xmlenc#sha512"></DigestMethod>
<DigestValue>q0y7dYggZ5NSeK7nP9fUEF56fskDfIncDizlb03YvRZNeLetgn0okYtleuVuq4yzDxtN1RGB5Ki5
RvkJ9g9s7A==</DigestValue>
</Reference>
<Reference URI=".metadata%2F.lock">
<DigestMethod Algorithm="http://www.w3.org/2001/04/xmlenc#sha512"></DigestMethod>
<DigestValue>z4PhNX7vuL3xVChQ1m2AB9Yg5AULVxXcg/SpIdNs6c5H0NE8XYXysP+DGNKHfuwvY7kxvUdBeoGl
ODJ6+SfaPg==</DigestValue>
</Reference>
<Reference URI=".metadata%2F.log">
<DigestMethod Algorithm="http://www.w3.org/2001/04/xmlenc#sha512"></DigestMethod>
<DigestValue>Jzq5gRW2Q0je8d53bQ+82YZp35u7j1cvBpR94OlhoMpqNQyzEsVHBvQ3nqZ92EnCorkFKB+2RQ7O
oi0W7Mh+TA==</DigestValue>
</Reference>
<Reference URI=".metadata%2F.plugins%2Forg.eclipse.cdt.core%2F.log">
<DigestMethod Algorithm="http://www.w3.org/2001/04/xmlenc#sha512"></DigestMethod>
<DigestValue>k1qk6Ce57TI4qMqn0LlBeTlrZnXk89jy1h/3+MWkLU6rFpMcjuJmbn2EbMC+n+qcDvQFazXNJJp8
d1bqduTNqQ==</DigestValue>
</Reference>
<Reference URI=".metadata%2F.plugins%2Forg.eclipse.cdt.make.core%2Fspecs.c">
<DigestMethod Algorithm="http://www.w3.org/2001/04/xmlenc#sha512"></DigestMethod>
<DigestValue>vmiIOMqGhuXJBom/KrWFzvETfJmbSMcLkvZ6XDTcFWl7XRHJgu1tcb4eHn97TgcziEqpfD96M5qO
0DV3z3S+CQ==</DigestValue>
</Reference>
<Reference URI=".metadata%2F.plugins%2Forg.eclipse.cdt.make.core%2Fspecs.cpp">
<DigestMethod Algorithm="http://www.w3.org/2001/04/xmlenc#sha512"></DigestMethod>
<DigestValue>vmiIOMqGhuXJBom/KrWFzvETfJmbSMcLkvZ6XDTcFWl7XRHJgu1tcb4eHn97TgcziEqpfD96M5qO
0DV3z3S+CQ==</DigestValue>
</Reference>
<Reference URI=".metadata%2F.plugins%2Forg.eclipse.core.resources%2F.root%2F.indexes%2Fhistory.version">
<DigestMethod Algorithm="http://www.w3.org/2001/04/xmlenc#sha512"></DigestMethod>
<DigestValue>+rhIybZXqFPuN8Ccv90UnQs4B7GR3em2I8zZUoHdGHBbSMibFQOQOEW7pXU5RTUf5rRUhSdg9zUp
zwHKj2ncyg==</DigestValue>
</Reference>
<Reference URI=".metadata%2F.plugins%2Forg.eclipse.core.resources%2F.root%2F.indexes%2Fproperties.index">
<DigestMethod Algorithm="http://www.w3.org/2001/04/xmlenc#sha512"></DigestMethod>
<DigestValue>1RGbSD5Ipl5qDA8UjPDoDria4vfdnajQ6bf+NbPZxnowjsRZfACJaDPRQnpDqxbny+E/ll9TYOSx
VvnynKlpMg==</DigestValue>
</Reference>
<Reference URI=".metadata%2F.plugins%2Forg.eclipse.core.resources%2F.root%2F.indexes%2Fproperties.version">
<DigestMethod Algorithm="http://www.w3.org/2001/04/xmlenc#sha512"></DigestMethod>
<DigestValue>e1S2aDbB+90T0kQdnhQ03GLKZ3+2j1/makZLqt7NvQBXb41rWsO8yAhEt9ULHMZgNES758/Pj8Cq
HuPGNtnjOQ==</DigestValue>
</Reference>
<Reference URI=".metadata%2F.plugins%2Forg.eclipse.core.resources%2F.root%2F1.tree">
<DigestMethod Algorithm="http://www.w3.org/2001/04/xmlenc#sha512"></DigestMethod>
<DigestValue>ayXKC2J/w+FP23agiivpt4v5B0xjJndudQNkJXuSeS9k5TOr/cwmtNWlt+zDeEZV29pM/YGAHJTs
67YxeZyblQ==</DigestValue>
</Reference>
<Reference URI=".metadata%2F.plugins%2Forg.eclipse.core.resources%2F.safetable%2Forg.eclipse.core.resources">
<DigestMethod Algorithm="http://www.w3.org/2001/04/xmlenc#sha512"></DigestMethod>
<DigestValue>YrztTlTtttDLl8c2IBkYREark/OSVIrcd1VaFR6coZNsxI2rc577SVAx561UMZqSHCbmB7aUTxMf
rlafjIRngA==</DigestValue>
</Reference>
<Reference URI=".metadata%2F.plugins%2Forg.eclipse.core.runtime%2F.settings%2Forg.eclipse.cdt.ui.prefs">
<DigestMethod Algorithm="http://www.w3.org/2001/04/xmlenc#sha512"></DigestMethod>
<DigestValue>vOrRj9lTN3x0iZkoMDL++Jd5OBRVJtWs4w4jbpfTUR7MocShl/Vo6+77a8xkhwiJVIrCulMed4JZ
FT71KYLpdQ==</DigestValue>
</Reference>
<Reference URI=".metadata%2F.plugins%2Forg.eclipse.core.runtime%2F.settings%2Forg.eclipse.core.resources.prefs">
<DigestMethod Algorithm="http://www.w3.org/2001/04/xmlenc#sha512"></DigestMethod>
<DigestValue>BdwoOu2TprkmYP1jF2VJOmvlDtLawSQ1yidrl5IDnjy7fA7eM6teMoeypyZd8ZyTO5F16GJn6dVl
+tOUsZwZAw==</DigestValue>
</Reference>
<Reference URI=".metadata%2F.plugins%2Forg.eclipse.core.runtime%2F.settings%2Forg.eclipse.debug.ui.prefs">
<DigestMethod Algorithm="http://www.w3.org/2001/04/xmlenc#sha512"></DigestMethod>
<DigestValue>VEIcOPly8W89G8TtJqSq1lzEBxoQzyTtL/A9FavVIUXArw+PI18wxmTP856YPVjl+zwEMr7/BNFu
kv8mjNnalw==</DigestValue>
</Reference>
<Reference URI=".metadata%2F.plugins%2Forg.eclipse.core.runtime%2F.settings%2Forg.eclipse.team.ui.prefs">
<DigestMethod Algorithm="http://www.w3.org/2001/04/xmlenc#sha512"></DigestMethod>
<DigestValue>PPy9aHbi+tFuvrjmMLz6VEni9EvSDwo+pSLq1t4cIv1ee1tfDcUL5CqEHmicN843nwe15cDkmRyU
LLf72a3CIQ==</DigestValue>
</Reference>
<Reference URI=".metadata%2F.plugins%2Forg.eclipse.core.runtime%2F.settings%2Forg.eclipse.ui.ide.prefs">
<DigestMethod Algorithm="http://www.w3.org/2001/04/xmlenc#sha512"></DigestMethod>
<DigestValue>xJ06GRHLmUd1Y9S39NavuMkizXIslWx51dTgCucrm9OATiBcoiftDtwfFNJxzXiiudDQAp70OXFl
P/f08hvIQA==</DigestValue>
</Reference>
<Reference URI=".metadata%2F.plugins%2Forg.eclipse.core.runtime%2F.settings%2Forg.eclipse.ui.workbench.prefs">
<DigestMethod Algorithm="http://www.w3.org/2001/04/xmlenc#sha512"></DigestMethod>
<DigestValue>mQxRRbRXYL1bV00kMsZOs058Jmx2sCl7zz9OoUe7vTbsQdm/REYOzOpWmzDEQYXrqQJrpZMs3p62
OQMkWaIHBw==</DigestValue>
</Reference>
<Reference URI=".metadata%2F.plugins%2Forg.eclipse.core.runtime%2F.settings%2Forg.eclipse.wst.jsdt.ui.prefs">
<DigestMethod Algorithm="http://www.w3.org/2001/04/xmlenc#sha512"></DigestMethod>
<DigestValue>cWfNOHgulGEZlys9b75TUjJwk0KJwQBB08AqBWix9sVFFo3S0O055On6CSl7aNsbi87MHVqehoa5
/Cqj2ysKTQ==</DigestValue>
</Reference>
<Reference URI=".metadata%2F.plugins%2Forg.eclipse.e4.workbench%2Fworkbench.xmi">
<DigestMethod Algorithm="http://www.w3.org/2001/04/xmlenc#sha512"></DigestMethod>
<DigestValue>jr8BmTkFquafuvqekFSDIsVLgqWg9Z9CqrlB/xkO0FpOictjKgoswIM9kPr01HyTWbJkalCPPLLI
IAPP1KMBeA==</DigestValue>
</Reference>
<Reference URI=".metadata%2F.plugins%2Forg.eclipse.ui.ide%2Fdialog_settings.xml">
<DigestMethod Algorithm="http://www.w3.org/2001/04/xmlenc#sha512"></DigestMethod>
<DigestValue>dQicBXY5IZFngr+o1KE8wKIFxPk8xaIJ2Lp3wJPx43R4bOkW1///lgqZhXmdiu/Pne9b2etik7FQ
qIdmRCGivA==</DigestValue>
</Reference>
<Reference URI=".metadata%2F.plugins%2Forg.eclipse.ui.workbench%2Fdialog_settings.xml">
<DigestMethod Algorithm="http://www.w3.org/2001/04/xmlenc#sha512"></DigestMethod>
<DigestValue>Ywe6BAoW7V3IUD9loFCncLgpS+q+Kehz0OkIqtHYuDgP43o+h7Xu3Zz3NhIH3A+yA4kvfHcvRQXE
aaHupjW/og==</DigestValue>
</Reference>
<Reference URI=".metadata%2F.plugins%2Forg.eclipse.ui.workbench%2Fworkingsets.xml">
<DigestMethod Algorithm="http://www.w3.org/2001/04/xmlenc#sha512"></DigestMethod>
<DigestValue>bQ2BOM1Bqh9ciFqk+rtWnJI8rfNFd+3yEn0Ki952puOz9YzMQdIygwQaNrTqXqYApjp/7LLunKXr
4OMdv+urzw==</DigestValue>
</Reference>
<Reference URI=".metadata%2F.plugins%2Forg.eclipse.wst.jsdt.core%2FvariablesAndContainers.dat">
<DigestMethod Algorithm="http://www.w3.org/2001/04/xmlenc#sha512"></DigestMethod>
<DigestValue>u4Qo0LZHZ/4wAuujPgIc2K6HWxaE7e6eNzFmlQiCeYQBzdy71hsEIk40wooXyqodgbvfFExHoMoD
I53Eb2VhAw==</DigestValue>
</Reference>
<Reference URI=".metadata%2F.plugins%2Forg.eclipse.wst.jsdt.ui%2FOpenTypeHistory.xml">
<DigestMethod Algorithm="http://www.w3.org/2001/04/xmlenc#sha512"></DigestMethod>
<DigestValue>YEwvaAO7dHBE12v/u6TYo2aQxaX5yU5RTw4E3sywepf4CnF0YxUl3IrQuJ8TNX8KEREUkagKUO6S
NVbdcSo4Uw==</DigestValue>
</Reference>
<Reference URI=".metadata%2F.plugins%2Forg.eclipse.wst.jsdt.ui%2FQualifiedTypeNameHistory.xml">
<DigestMethod Algorithm="http://www.w3.org/2001/04/xmlenc#sha512"></DigestMethod>
<DigestValue>vPVmGsz2/j5FjxmzT819PIb1yrxX5hgqVGtUGWnWlSE9Y/n1V1/6aDFrdsT2fxbTxaa4kyduOC3w
v/b5cYvdEQ==</DigestValue>
</Reference>
<Reference URI=".metadata%2F.plugins%2Forg.tizen.common.sign%2Fmigrated">
<DigestMethod Algorithm="http://www.w3.org/2001/04/xmlenc#sha512"></DigestMethod>
<DigestValue>z4PhNX7vuL3xVChQ1m2AB9Yg5AULVxXcg/SpIdNs6c5H0NE8XYXysP+DGNKHfuwvY7kxvUdBeoGl
ODJ6+SfaPg==</DigestValue>
</Reference>
<Reference URI=".metadata%2Fversion.ini">
<DigestMethod Algorithm="http://www.w3.org/2001/04/xmlenc#sha512"></DigestMethod>
<DigestValue>XOBFLzEWOw5uZ3Qq+dcVrq3UBkHAhUvGkqfegPNl1OcE39s0lCIP1ykeJAa6gn04jqZ9g2Kx574N
hz3KLl+xRw==</DigestValue>
</Reference>
<Reference URI="AUTHORS">
<DigestMethod Algorithm="http://www.w3.org/2001/04/xmlenc#sha512"></DigestMethod>
<DigestValue>quFVIY21+TBnE0PlPc6dDwllRvMOIO+L6iNmr2NHBVfpAQk3xN23OGwHV5vcLJzxOfZ9C+32/g06
+sBjb2hYOw==</DigestValue>
</Reference>
<Reference URI="LICENSE.Flora">
<DigestMethod Algorithm="http://www.w3.org/2001/04/xmlenc#sha512"></DigestMethod>
<DigestValue>eMZs49Zoyv8pka7rh1hDfAR9c0J1Mc3Go+Yd/8y3382XiW4+49kRz7KJzjH959FGl3xkQZDNDYWt
3juskmdDvg==</DigestValue>
</Reference>
<Reference URI="NOTICE">
<DigestMethod Algorithm="http://www.w3.org/2001/04/xmlenc#sha512"></DigestMethod>
<DigestValue>6R2XTNsDCKoqH5wUr+gWDc4Fk6sDBYTdubXgZ/fXy6GFuHpRM/cewjZBdvYckJd47pCsTFMgpRX1
UOFkMrvkjg==</DigestValue>
</Reference>
<Reference URI="config.xml">
<DigestMethod Algorithm="http://www.w3.org/2001/04/xmlenc#sha512"></DigestMethod>
<DigestValue>wkKEItjTRwPACq7TBDavu/Ks21T/bWsdrryd0OegzIxacXqMWlVgW2E4cTsHxAEI6oKl88nhLR7j
6NlvhvnU1w==</DigestValue>
</Reference>
<Reference URI="css%2Fstyle.css">
<DigestMethod Algorithm="http://www.w3.org/2001/04/xmlenc#sha512"></DigestMethod>
<DigestValue>GkoEAof6GT5IIdrYakM55KrpOpFS/q9ir2GKyAO5G4bmgzyap2YppwdMa1EHrdH14Ud/o/4+z3uU
zwr8AMC2Uw==</DigestValue>
</Reference>
<Reference URI="icon.png">
<DigestMethod Algorithm="http://www.w3.org/2001/04/xmlenc#sha512"></DigestMethod>
<DigestValue>GrMyl/B7KXon04Nqn2eUPmUUcXKWfK+f2ubAlrJd2aKXPHeXBmyUClZZzsDZabVyvZRGLOH0fTve
rToipOmUoA==</DigestValue>
</Reference>
<Reference URI="icon2.png">
<DigestMethod Algorithm="http://www.w3.org/2001/04/xmlenc#sha512"></DigestMethod>
<DigestValue>GKaAX2XA1x2ytXpunzpCzpNiM6szLhEWk+UyKGzAgx6iEs49HNlzLVsTXm2dYiWvEZiiTMz2U6lh
WCLpOpkL0w==</DigestValue>
</Reference>
<Reference URI="images%2Fgenie.png">
<DigestMethod Algorithm="http://www.w3.org/2001/04/xmlenc#sha512"></DigestMethod>
<DigestValue>OjJwOrur0QLfFHx0TikGPM7F1eXExWIoIN0WUHuP7rK/vCeciYUZ5Mhe1EYxmQcO0OrFSBU/7WaG
vrl9BqwDlQ==</DigestValue>
</Reference>
<Reference URI="index.html">
<DigestMethod Algorithm="http://www.w3.org/2001/04/xmlenc#sha512"></DigestMethod>
<DigestValue>uEdhf6ID169h4zczrlMt5U/ouFBhc+tPoMG3t1xYQswnkYkCFrzxAr9EjUrrVl6fpjrkxBVJSzht
zXt2TQc8/A==</DigestValue>
</Reference>
<Reference URI="js%2Fmain.js">
<DigestMethod Algorithm="http://www.w3.org/2001/04/xmlenc#sha512"></DigestMethod>
<DigestValue>0nc6S3HUfUc0y/2tBxp+eYE2GTUXL0yfbK3vSbS9AyYWc1ZxGqTsizfow0v1GPcyLyze5KqULY4i
3VIva77C9w==</DigestValue>
</Reference>
<Reference URI="welcome.html">
<DigestMethod Algorithm="http://www.w3.org/2001/04/xmlenc#sha512"></DigestMethod>
<DigestValue>bTwNHLBRYxHpN7eWWqMlhBsLNtp8rcrRmzE7qSPYzjIER6jd/iaDEOlKN0P0VRzhSnzc7eBUljjS
qYez730lTg==</DigestValue>
</Reference>
<Reference URI="#prop">
<Transforms>
<Transform Algorithm="http://www.w3.org/2006/12/xml-c14n11"></Transform>
</Transforms>
<DigestMethod Algorithm="http://www.w3.org/2001/04/xmlenc#sha512"></DigestMethod>
<DigestValue>aXbSAVgmAz0GsBUeZ1UmNDRrxkWhDUVGb45dZcNRq429wX3X+x6kaXT3NdNDTSNVTU+ypkysPMGv
QY10fG1EWQ==</DigestValue>
</Reference>
</SignedInfo>
<SignatureValue>
Ldsrgc0lFyp58m4tNiE162LWAcv4O2znv4IlB0p/pSbks9GboN99RdNfY8Nc/VRorZFMpdNhbcU9
UPMMzWyuVFuX2jaEumwMwEApvwaXmaSUS0jQZCmhn20nhx5g6sywSFX0FUY/1wOmW4pxxvDXsgrc
mRZ06cU10Z6rjqOrOlk=
</SignatureValue>
<KeyInfo>
<X509Data>
<X509Certificate>
MIIC0TCCAbmgAwIBAgIGAXsfn5+ZMA0GCSqGSIb3DQEBDQUAMFYxGjAYBgNVBAoMEVRpemVuIEFz
c29jaWF0aW9uMRowGAYDVQQLDBFUaXplbiBBc3NvY2lhdGlvbjEcMBoGA1UEAwwTVGl6ZW4gRGV2
ZWxvcGVycyBDQTAeFw0yMTA4MDcwNzU5MTlaFw0yNzAxMDEwMDAwMDBaME0xCzAJBgNVBAYTAkJE
MQ4wDAYDVQQIDAVEaGFrYTEOMAwGA1UEBwwFRGhha2ExDjAMBgNVBAoMBUdlbmllMQ4wDAYDVQQD
DAVHZW5pZTCBnzANBgkqhkiG9w0BAQEFAAOBjQAwgYkCgYEA1RcJb/dpWjXbcyOWDm753VgmRsPo
90ooAlkWkgNVTKVLgzSt3VLz1/iqjpt+G58PLAilJqg2rcVSZIRm96TMLVJXtw0MT412MHa2uRIp
yadD1x8EQG5bcJDCOnMHQgPg1fBXKolN24A1nlchiH6+0hBXtbihHrsMtRiAkCBu4q8CAwEAAaMy
MDAwDAYDVR0TAQH/BAIwADALBgNVHQ8EBAMCB4AwEwYDVR0lBAwwCgYIKwYBBQUHAwMwDQYJKoZI
hvcNAQENBQADggEBADMRTe1mnNrfF1YJ7rZtqrM5m450kt3bWqL0vtZ7hkM6NB/yM6dzIqiVPcV3
HFGDAQ4JQwhY/0AiBqhJDYDGv5EpwoV3eA0d1Q4X+dZkGazcCZeKtALdcc9yuYHUfrAPONo18ciR
zWfQIm7oHVgt/NWD87+igWby5AGpnOtmz+isXkE4iDOjEZ9/y7o0eRJdAKLKbOOnG7FjNykBlrVp
yoVYlbg1iB0nzzS5Otf3TsFjNZCzieHSsy1RTsG3VRk3aZBuyUj/sHTdOzQfNDs46yCXGxSVwhZU
LDhIA2U8QUii4kXWdPegT420P6YRH2T2Xg+haMyxqPxCpUsfuk1BRI4=
</X509Certificate>
<X509Certificate>
MIIDOTCCAiGgAwIBAgIBATANBgkqhkiG9w0BAQUFADBYMRowGAYDVQQKDBFUaXplbiBBc3NvY2lh
dGlvbjEaMBgGA1UECwwRVGl6ZW4gQXNzb2NpYXRpb24xHjAcBgNVBAMMFVRpemVuIERldmVsb3Bl
cnMgUm9vdDAeFw0xMjAxMDEwMDAwMDBaFw0yNzAxMDEwMDAwMDBaMFYxGjAYBgNVBAoMEVRpemVu
IEFzc29jaWF0aW9uMRowGAYDVQQLDBFUaXplbiBBc3NvY2lhdGlvbjEcMBoGA1UEAwwTVGl6ZW4g
RGV2ZWxvcGVycyBDQTCCASIwDQYJKoZIhvcNAQEBBQADggEPADCCAQoCggEBANVGhRGmMIUyBA7o
PCz8Sxut6z6HNkF4oDIuzuKaMzRYPeWodwe9O0gmqAkToQHfwg2giRhE5GoPld0fq+OYMMwSasCu
g8dwODx1eDeSYVuOLWRxpAmbTXOsSFi6VoWeyaPEm18JBHvZBsU5YQtgZ6Kp7MqzvQg3pXOxtajj
vyHxiatJl+xXrHgcXC1wgyG3buty7u/Fi2mvKXJ0PRJcCjjK81dqe/Vr20sRUCrbk02zbm5ggFt/
jIEhV8wbFRQpliobc7J4dSTKhFfrqGM8rdd54LYhD7gSI1CFSe16pUXfcVR7FhJztRaiGLnCrwBE
dyTZ248+D4L/qR/D0axb3jcCAwEAAaMQMA4wDAYDVR0TBAUwAwEB/zANBgkqhkiG9w0BAQUFAAOC
AQEAnOXXQ/1O/QTDHyrmQDtFziqPY3xWlJBqJtEqXiT7Y+Ljpe66e+Ee/OjQMlZe8gu21/8cKklH
95RxjopMWCVedXDUbWdvS2+CdyvVW/quT2E0tjqIzXDekUTYwwhlPWlGxvfj3VsxqSFq3p8Brl04
1Gx5RKAGyKVsMfTLhbbwSWwApuBUxYfcNpKwLWGPXkysu+HctY03OKv4/xKBnVWiN8ex/Sgesi0M
+OBAOMdZMPK32uJBTeKFx1xZgTLIhk45V0hPOomPjZloiv0LSS11eyd451ufjW0iHRE7WlpR6EvI
W6TFyZgMpQq+kg4hWl2SBTf3s2VI8Ygz7gj8TMlClg==
</X509Certificate>
</X509Data>
</KeyInfo>
<Object Id="prop"><SignatureProperties xmlns:dsp="http://www.w3.org/2009/xmldsig-properties"><SignatureProperty Id="profile" Target="#AuthorSignature"><dsp:Profile URI="http://www.w3.org/ns/widgets-digsig#profile"></dsp:Profile></SignatureProperty><SignatureProperty Id="role" Target="#AuthorSignature"><dsp:Role URI="http://www.w3.org/ns/widgets-digsig#role-author"></dsp:Role></SignatureProperty><SignatureProperty Id="identifier" Target="#AuthorSignature"><dsp:Identifier></dsp:Identifier></SignatureProperty></SignatureProperties></Object>
</Signature>